eugene/__init__.py
eugene/scripts_demos/LotkaVolterraDemo.py
eugene/scripts_demos/__init__.py
eugene/src/__init__.py
eugene/src/categorize.py
eugene/src/compare.py
eugene/src/interface.py
eugene/src/auxiliary/__init__.py
eugene/src/auxiliary/csv_to_dataframe.py
eugene/src/auxiliary/probability.py
eugene/src/connect/__init__.py
eugene/src/connect/actuators.py
eugene/src/connect/sensors.py
eugene/src/virtual_sys/LotkaVolterra2D.py
eugene/src/virtual_sys/__init__.py
eugene/src/virtual_sys/chaotic_circuits.py
eugene/src/virtual_sys/chemical_sys.py
eugene/src/virtual_sys/circuitparams.py
eugene/src/virtual_sys/growth_sys.py
eugene/src/virtual_sys/lorenz.py
eugene/tests/__init__.py
eugene/tests/test_compare.py
eugene-0.1.0.dist-info/DESCRIPTION.rst
eugene-0.1.0.dist-info/METADATA
eugene-0.1.0.dist-info/RECORD
eugene-0.1.0.dist-info/WHEEL
eugene-0.1.0.dist-info/metadata.json
eugene-0.1.0.dist-info/top_level.txt
