Metadata-Version: 2.0
Name: eugene
Version: 0.1.0
Summary: Tools for automated scientific discovery
Home-page: http://www.ratiocination.org/
Author: Benjamin C. Jantzen
Author-email: bjantzen@vt.edu
License: MIT
Download-URL: https://github.com/jantzen/eugene
Keywords: discovery kinds dynamical system-identification natural-kinds
Platform: UNKNOWN
Classifier: Development Status :: 3 - Alpha
Classifier: Intended Audience :: Science/Research
Classifier: Topic :: Scientific/Engineering :: Artificial Intelligence
Classifier: License :: OSI Approved :: MIT License
Classifier: Programming Language :: Python :: 2
Classifier: Programming Language :: Python :: 2.7
Classifier: Programming Language :: Python :: 3
Classifier: Programming Language :: Python :: 3.3
Classifier: Programming Language :: Python :: 3.4
Classifier: Programming Language :: Python :: 3.5
Requires-Dist: numpy
Requires-Dist: scipy
